MANIFEST.in
README.md
setup.cfg
setup.py
bin/todo-cli.py
commenttodo.egg-info/PKG-INFO
commenttodo.egg-info/SOURCES.txt
commenttodo.egg-info/dependency_links.txt
commenttodo.egg-info/entry_points.txt
commenttodo.egg-info/requires.txt
commenttodo.egg-info/top_level.txt
todocli/__init__.py
todocli/todo_cli.py
todocli/tests/__init__.py
todocli/tests/test_todo_cli.py
todocli/tests/test_todo/__init__.py
todocli/tests/test_todo/test_commands.py
todocli/tests/test_todo/test_config.py
todocli/tests/test_todo/test_configmenusetup.py
todocli/tests/test_todo/test_reader.py
todocli/tests/test_todo/test_writer.py
todocli/todo/__init__.py
todocli/todo/commands.py
todocli/todo/config.py
todocli/todo/configmenusetup.py
todocli/todo/reader.py
todocli/todo/writer.py
todocli/todo/utils/__init__.py
todocli/todo/utils/bool_arg_parser.py
todocli/todo/utils/comment.py
todocli/todo/utils/file.py
todocli/todo/utils/utils.py