Metadata-Version: 2.1
Name: commenttodo
Version: 0.0-1
Summary: CLI that shows all TODO comments in your files
Home-page: https://github.com/BalenD/TODO-cli
Author: BalenD
Author-email: Balen1996@hotmail.com
License: MIT
Project-URL: Documentation, https://github.com/BalenD/TODO-cli
Project-URL: Issue Tracker, https://github.com/BalenD/TODO-cli/issues
Platform: UNKNOWN
Classifier: Programming Language :: Python :: 3
Classifier: License :: OSI Approved :: MIT License
Classifier: Operating System :: OS Independent
